fitkit/__init__.py
fitkit-0.2.1.dist-info/LICENSE
fitkit-0.2.1.dist-info/METADATA
fitkit-0.2.1.dist-info/WHEEL
fitkit-0.2.1.dist-info/top_level.txt
fitkit-0.2.1.dist-info/RECORD
