Metadata-Version: 2.1
Name: fitkit
Version: 0.2.1
Summary: Fit and inspect statistical models.
Home-page: https://github.com/okasag/fitkit.git
Author: Gabriel Okasa and Kenneth Younge
Author-email: gabriel.okasa@epfl.ch
License: UNKNOWN
Platform: UNKNOWN
Classifier: Programming Language :: Python :: 3
Classifier: License :: OSI Approved :: MIT License
Classifier: Operating System :: OS Independent
Requires-Python: >=3.6
License-File: LICENSE
